mailpush/__init__.py
mailpush/client.py
mailpush/errors.py
mailpush/types.py
mailpush/resources/__init__.py
mailpush/resources/emails.py
mailpush-0.1.0.dist-info/METADATA
mailpush-0.1.0.dist-info/WHEEL
mailpush-0.1.0.dist-info/top_level.txt
mailpush-0.1.0.dist-info/RECORD
