Metadata-Version: 2.4
Name: mailpush
Version: 0.1.0
Summary: Official Mailpush SDK for Python
Author-email: Mailpush <contact@mailpush.app>
License: MIT
Project-URL: Homepage, https://mailpush.app
Project-URL: Documentation, https://mailpush.app/docs
Project-URL: Repository, https://github.com/Dilgo-dev/mailpush
Project-URL: Issues, https://github.com/Dilgo-dev/mailpush/issues
Keywords: email,api,mailpush,sdk,transactional
Classifier: Development Status :: 4 - Beta
Classifier: Intended Audience :: Developers
Classifier: License :: OSI Approved :: MIT License
Classifier: Programming Language :: Python :: 3
Classifier: Programming Language :: Python :: 3.8
Classifier: Programming Language :: Python :: 3.9
Classifier: Programming Language :: Python :: 3.10
Classifier: Programming Language :: Python :: 3.11
Classifier: Programming Language :: Python :: 3.12
Classifier: Topic :: Communications :: Email
Classifier: Typing :: Typed
Requires-Python: >=3.8
Requires-Dist: requests>=2.25.0
Provides-Extra: dev
Requires-Dist: pytest>=7.0.0; extra == "dev"
Requires-Dist: pytest-cov>=4.0.0; extra == "dev"
Requires-Dist: responses>=0.23.0; extra == "dev"
